LICENSE
MANIFEST.in
README.md
setup.cfg
setup.py
eec/__init__.py
eec/eeccomps.pxd
eec/eeccore.cpp
eec/eeccore.pyx
eec.egg-info/PKG-INFO
eec.egg-info/SOURCES.txt
eec.egg-info/dependency_links.txt
eec.egg-info/not-zip-safe
eec.egg-info/requires.txt
eec.egg-info/top_level.txt
eec/include/EEC.hh
eec/include/EECBase.hh
eec/include/EECHist.hh
eec/include/EECLongestSide.hh
eec/include/EECTriangleOPE.hh
eec/include/boost/assert.hpp
eec/include/boost/config.hpp
eec/include/boost/cstdint.hpp
eec/include/boost/current_function.hpp
eec/include/boost/histogram.hpp
eec/include/boost/limits.hpp
eec/include/boost/mp11.hpp
eec/include/boost/throw_exception.hpp
eec/include/boost/type.hpp
eec/include/boost/version.hpp
eec/include/boost/assert/source_location.hpp
eec/include/boost/config/abi_prefix.hpp
eec/include/boost/config/abi_suffix.hpp
eec/include/boost/config/auto_link.hpp
eec/include/boost/config/header_deprecated.hpp
eec/include/boost/config/helper_macros.hpp
eec/include/boost/config/pragma_message.hpp
eec/include/boost/config/requires_threads.hpp
eec/include/boost/config/user.hpp
eec/include/boost/config/warning_disable.hpp
eec/include/boost/config/workaround.hpp
eec/include/boost/config/abi/borland_prefix.hpp
eec/include/boost/config/abi/borland_suffix.hpp
eec/include/boost/config/abi/msvc_prefix.hpp
eec/include/boost/config/abi/msvc_suffix.hpp
eec/include/boost/config/compiler/borland.hpp
eec/include/boost/config/compiler/clang.hpp
eec/include/boost/config/compiler/codegear.hpp
eec/include/boost/config/compiler/comeau.hpp
eec/include/boost/config/compiler/common_edg.hpp
eec/include/boost/config/compiler/compaq_cxx.hpp
eec/include/boost/config/compiler/cray.hpp
eec/include/boost/config/compiler/diab.hpp
eec/include/boost/config/compiler/digitalmars.hpp
eec/include/boost/config/compiler/gcc.hpp
eec/include/boost/config/compiler/gcc_xml.hpp
eec/include/boost/config/compiler/greenhills.hpp
eec/include/boost/config/compiler/hp_acc.hpp
eec/include/boost/config/compiler/intel.hpp
eec/include/boost/config/compiler/kai.hpp
eec/include/boost/config/compiler/metrowerks.hpp
eec/include/boost/config/compiler/mpw.hpp
