Metadata-Version: 2.1
Name: eec
Version: 0.1.6
Summary: EEC computations in python
Home-page: https://github.com/pkomiske/EnergyEnergyCorrelators
Author: Patrick T. Komiske III
Author-email: pkomiske@mit.edu
License: GPL-3.0
Platform: UNKNOWN
Requires-Python: >=3.4
